<PasswordPatterns>
    <Pattern>\bpass\b</Pattern>
    <Pattern>\bmdp\b</Pattern>
    <Pattern>\bsecret\b</Pattern>
    <Pattern>\bssh-key\b</Pattern>
    <Pattern>\bprivate-key\b</Pattern>
    <Pattern>\bapikey\b</Pattern>
    <Pattern>\baccesskey\b</Pattern>
    <Pattern>\btoken\b</Pattern>
    <Pattern>\blogin\b</Pattern>
    <Pattern>\bidentifiant\b</Pattern>
    <Pattern>\bauth\b</Pattern>
    <Pattern>credentials</Pattern>
    <Pattern>\bcred\b</Pattern>
    <Pattern>\bpwd\b</Pattern>
    <Pattern>\bmotdepasse\b</Pattern>
    <Pattern>\bmdpass\b</Pattern>
    <Pattern>\bmotdepasse\b</Pattern>
    <Pattern>password</Pattern>
	<Pattern>net use</Pattern>
</PasswordPatterns>
